[{"eng":"The Past Simple Tense","tr":"Простое прошедшее время","help":""},{"eng":"Where did Tom go?","tr":"Куда пошёл Том?","help":""},{"eng":"go - went - gone","tr":"идти - 3 формы","help":"go"},{"eng":"The Past Simple Tense","tr":"Простое прошедшее время","help":""},{"eng":"go - went - gone","tr":"идти - 3 формы","help":"go"},{"eng":"Where did Tom go?","tr":"Куда пошёл Том?","help":""},{"eng":"catch - caught - caught","tr":"хватать - 3 формы","help":""},{"eng":"make a quick stop at the store","tr":"'заскочить' в магазин","help":""},{"eng":"Do you often take it?","tr":"Ты часто берешь это?","help":""},{"eng":"Do they sometimes meet?","tr":"Они иногда встречаются?","help":""},{"eng":"Does it ever work?","tr":"Это* вообще работает?","help":""},{"eng":"Do you rarely build?","tr":"Ты редко строишь?","help":""},{"eng":"Does it always work?","tr":"Это всегда работает?","help":""},{"eng":"Sometimes I read. — Do you?","tr":"Иногда я читаю. — Действительно*?","help":"должно звучать \"риид\""},{"eng":"She often do it. — Does she?","tr":"Она часто это делает. — Правда*?","help":""},{"eng":"He sometimes drinks. — Does he?","tr":"Он иногда пьет. — Правда*?","help":""},{"eng":"He often swims here. — Does he?","tr":"Он часто плавает здесь. — Точно*?","help":""}]