[{"eng":"the same","tr":"тоже самое","help":""},{"eng":"to sing ","tr":"() петь","help":""},{"eng":"to meet","tr":"() встречать","help":""},{"eng":"Do you always buy the same?","tr":"Ты всегда покупаешь тоже самое?","help":""},{"eng":"Does she ever sing?","tr":"Она вообще поет?","help":""},{"eng":"Do they rarely meet?","tr":"Они редко встречаются?","help":""},{"eng":"Does it always work?","tr":"Это всегда работает?","help":""},{"eng":"to read","tr":"() читать","help":""},{"eng":"to choose","tr":"() выбирать","help":""},{"eng":"Do you sometimes read?","tr":"Ты иногда читаешь?","help":""},{"eng":"Does he always choose the same?","tr":"Он всегда выбирает одно и то же?","help":""},{"eng":"to learn","tr":"() учить, познавать","help":""},{"eng":"to begin","tr":"() начинать","help":""},{"eng":"to drink","tr":"() пить","help":""},{"eng":"Do you ever learn English?","tr":"Ты вообще учишь английский?","help":"lɜrn"},{"eng":"Does she often do it?","tr":"Она часто это делает?","help":""},{"eng":"Do they usually begin at five?","tr":"Они обычно начинают в пять?","help":""},{"eng":"Does he rarely go there?","tr":"Он редко ходит туда?","help":""},{"eng":"Do you ever drink coffee?","tr":"Ты вообще пьешь кофе?","help":""},{"eng":"to sleep","tr":"() спать","help":""},{"eng":"to write","tr":"() писать","help":""},{"eng":"to burn","tr":"() гореть","help":""},{"eng":"Does she usually sleep there?","tr":"Она обычно спит там?","help":""},{"eng":"Do they rarely write SMS?","tr":"Они редко пишут СМС?","help":""},{"eng":"Does it always burn?","tr":"Это всегда горит?","help":""}]